__init__.py
compile.py
compile-1.0.2.dist-info/LICENSE.txt
compile-1.0.2.dist-info/METADATA
compile-1.0.2.dist-info/WHEEL
compile-1.0.2.dist-info/entry_points.txt
compile-1.0.2.dist-info/top_level.txt
compile-1.0.2.dist-info/RECORD
