Metadata-Version: 2.1
Name: compile
Version: 1.0.2
Summary: Compiling Python source code into bytecode in production environment
Home-page: https://github.com/lyymoo/compile
Author: moz
Author-email: m@lee.mo.cn
License: UNKNOWN
Platform: UNKNOWN
Classifier: Programming Language :: Python :: 3
Classifier: License :: OSI Approved :: MIT License
Classifier: Operating System :: OS Independent
